myconstants/__init__.py
myconstants/policies.py
apsniper0673_constants-0.1.11.dist-info/METADATA
apsniper0673_constants-0.1.11.dist-info/WHEEL
apsniper0673_constants-0.1.11.dist-info/top_level.txt
apsniper0673_constants-0.1.11.dist-info/RECORD
