Metadata-Version: 2.4
Name: apsniper0673_constants
Version: 0.1.11
Summary: My constants for APSniper0673
Author: apsniper0673
Requires-Python: >=3.8
